README.md
setup.cfg
setup.py
dmsp/__init__.py
dmsp/io.py
dmsp/plots.py
dmsp.egg-info/PKG-INFO
dmsp.egg-info/SOURCES.txt
dmsp.egg-info/dependency_links.txt
dmsp.egg-info/entry_points.txt
dmsp.egg-info/requires.txt
dmsp.egg-info/top_level.txt