Metadata-Version: 2.1
Name: dmsp
Version: 0.6.0
Summary: Load and plot UAF Geophysical Institute Digital Meridian Spectrometer data
Home-page: https://github.com/scivision/meridian-spectrometer-reader
Author: Michael Hirsch, Ph.D.
License: UNKNOWN
Keywords: aurora,spectrograph
Platform: UNKNOWN
Classifier: Development Status :: 4 - Beta
Classifier: Environment :: Console
Classifier: Intended Audience :: Science/Research
Classifier: License :: OSI Approved :: MIT License
Classifier: Programming Language :: Python :: 3.6
Classifier: Programming Language :: Python :: 3.7
Classifier: Topic :: Scientific/Engineering :: Atmospheric Science
Requires-Python: >= 3.6
Provides-Extra: plot
Provides-Extra: tests
Provides-Extra: cov
